step/__init__.py
step/component.py
step/epoch.py
step/input.py
step/participant.py
step/preproc.py
step/datasets/__init__.py
step/datasets/erpcore.py
step/datasets/erpcore_manifest.csv
step/datasets/ucap.py
step/datasets/ucap_manifest.csv
step/datasets/utils.py
eeg_step-0.0.3.dist-info/METADATA
eeg_step-0.0.3.dist-info/WHEEL
eeg_step-0.0.3.dist-info/licenses/LICENSE.md
eeg_step-0.0.3.dist-info/RECORD
