Metadata-Version: 2.3
Name: eeg-step
Version: 0.0.3
Summary: Single-trial EEG pipeline
Project-URL: Changelog, https://github.com/alexenge/eeg-step/releases
Project-URL: Documentation, https://readthedocs.org/projects/eeg-step
Project-URL: Issues, https://github.com/alexenge/eeg-step/issues
Project-URL: Repository, https://github.com/alexenge/eeg-step
Author-email: Alexander Enge <alex_enge@web.de>
License: # MIT License
Keywords: eeg,electroencephalography,neuroscience,psychology,research,science
Classifier: Development Status :: 3 - Alpha
Classifier: Intended Audience :: Science/Research
Classifier: License :: OSI Approved :: MIT License
Classifier: Operating System :: OS Independent
Classifier: Programming Language :: Python
Classifier: Programming Language :: Python :: 3
Classifier: Programming Language :: Python :: 3.9
Classifier: Programming Language :: Python :: 3.10
Classifier: Programming Language :: Python :: 3.11
Classifier: Programming Language :: Python :: 3.12
Classifier: Programming Language :: Python :: 3.13
Classifier: Programming Language :: Python :: 3.14
Classifier: Topic :: Scientific/Engineering
Requires-Python: >=3.9
Requires-Dist: chardet
Requires-Dist: eeg-ride
Requires-Dist: joblib
Requires-Dist: matplotlib
Requires-Dist: mne
Requires-Dist: pandas
Requires-Dist: pooch
Requires-Dist: scikit-learn
Provides-Extra: docs
Requires-Dist: furo; extra == 'docs'
Requires-Dist: myst-parser; extra == 'docs'
Requires-Dist: sphinx; extra == 'docs'
Requires-Dist: sphinx-autodoc-typehints; extra == 'docs'
Requires-Dist: sphinx-copybutton; extra == 'docs'
